{
  "boxes": [
    {
      "id": 1,
      "type": "start",
      "parentId": null,
      "hasChild": false,
      "tags": ["segments", "campaigns"],
      "data": {
        "name": "initial box",
        "createdDate": "2021-03-03",
        "isActive": true
      }
    },
    {
      "id": 2,
      "type": "email",
      "parentId": 1,
      "hasChild": false,
      "data": {
        "name": "email box",
        "createdDate": "2021-03-03",
        "isActive": true
      }
    },
    {
      "id": 3,
      "type": "timer",
      "parentId": 2,
      "hasChild": false,
      "data": {
        "name": "timer box",
        "createdDate": "2021-03-03",
        "isActive": true
      }
    }
  ]
}
